Metadata-Version: 2.4
Name: chatops
Version: 0.9.2
Summary: Command line toolkit for operations teams
Author: Franck Kengne
Requires-Python: >=3.8
Requires-Dist: typer>=0.9
Requires-Dist: rich>=13
Requires-Dist: requests>=2.31
Requires-Dist: PyYAML>=6
Requires-Dist: openai<2,>=1.0
Requires-Dist: boto3>=1.28
Requires-Dist: docker>=6
